imagic/__init__.py
imagic/bibtex.py
imagic/constants.py
imagic/protocols.conf
imagic/utils.py
imagic/viewers.py
imagic/wizards.py
imagic/protocols/__init__.py
imagic/protocols/protocol_base.py
imagic/protocols/protocol_msa.py
imagic/protocols/protocol_msa_classify.py
imagic/scripts/190830/msa/msa-cls.b
imagic/scripts/190830/msa/msa-run.b
imagic/tests/__init__.py
imagic/tests/test_workflow_imagicMSA.py
scipion_em_imagic-3.0.14.dist-info/LICENSE
scipion_em_imagic-3.0.14.dist-info/METADATA
scipion_em_imagic-3.0.14.dist-info/WHEEL
scipion_em_imagic-3.0.14.dist-info/entry_points.txt
scipion_em_imagic-3.0.14.dist-info/top_level.txt
scipion_em_imagic-3.0.14.dist-info/RECORD
